{
  "type": "FeatureCollection",
  "features": [
    {"type":"Feature","properties":{"name":"United States"},"geometry":{"type":"Polygon","coordinates":[[[-125,24],[-66,24],[-66,49],[-125,49],[-125,24]]]}},
    {"type":"Feature","properties":{"name":"Canada"},"geometry":{"type":"Polygon","coordinates":[[[-141,49],[-52,49],[-52,70],[-141,70],[-141,49]]]}},
    {"type":"Feature","properties":{"name":"Brazil"},"geometry":{"type":"Polygon","coordinates":[[[-74,-34],[-34,-34],[-34,5],[-74,5],[-74,-34]]]}},
    {"type":"Feature","properties":{"name":"United Kingdom"},"geometry":{"type":"Polygon","coordinates":[[[-8,50],[2,50],[2,59],[-8,59],[-8,50]]]}},
    {"type":"Feature","properties":{"name":"France"},"geometry":{"type":"Polygon","coordinates":[[[-5,42],[8,42],[8,51],[-5,51],[-5,42]]]}},
    {"type":"Feature","properties":{"name":"Germany"},"geometry":{"type":"Polygon","coordinates":[[[5,47],[16,47],[16,55],[5,55],[5,47]]]}},
    {"type":"Feature","properties":{"name":"Spain"},"geometry":{"type":"Polygon","coordinates":[[[-9,36],[3,36],[3,44],[-9,44],[-9,36]]]}},
    {"type":"Feature","properties":{"name":"Ukraine"},"geometry":{"type":"Polygon","coordinates":[[[22,44],[41,44],[41,52],[22,52],[22,44]]]}},
    {"type":"Feature","properties":{"name":"Russia"},"geometry":{"type":"Polygon","coordinates":[[[30,50],[180,50],[180,75],[30,75],[30,50]]]}},
    {"type":"Feature","properties":{"name":"Israel"},"geometry":{"type":"Polygon","coordinates":[[[34,29],[36,29],[36,34],[34,34],[34,29]]]}},
    {"type":"Feature","properties":{"name":"Palestine"},"geometry":{"type":"Polygon","coordinates":[[[34.2,31],[35.6,31],[35.6,32.5],[34.2,32.5],[34.2,31]]]}},
    {"type":"Feature","properties":{"name":"Syria"},"geometry":{"type":"Polygon","coordinates":[[[35,32],[42,32],[42,37],[35,37],[35,32]]]}},
    {"type":"Feature","properties":{"name":"Turkey"},"geometry":{"type":"Polygon","coordinates":[[[26,36],[45,36],[45,42],[26,42],[26,36]]]}},
    {"type":"Feature","properties":{"name":"Iran"},"geometry":{"type":"Polygon","coordinates":[[[44,25],[63,25],[63,40],[44,40],[44,25]]]}},
    {"type":"Feature","properties":{"name":"India"},"geometry":{"type":"Polygon","coordinates":[[[68,7],[89,7],[89,35],[68,35],[68,7]]]}},
    {"type":"Feature","properties":{"name":"Pakistan"},"geometry":{"type":"Polygon","coordinates":[[[60,24],[77,24],[77,37],[60,37],[60,24]]]}},
    {"type":"Feature","properties":{"name":"China"},"geometry":{"type":"Polygon","coordinates":[[[73,18],[135,18],[135,53],[73,53],[73,18]]]}},
    {"type":"Feature","properties":{"name":"Japan"},"geometry":{"type":"Polygon","coordinates":[[[129,31],[146,31],[146,45],[129,45],[129,31]]]}},
    {"type":"Feature","properties":{"name":"South Korea"},"geometry":{"type":"Polygon","coordinates":[[[126,34],[130,34],[130,39],[126,39],[126,34]]]}},
    {"type":"Feature","properties":{"name":"Australia"},"geometry":{"type":"Polygon","coordinates":[[[112,-44],[154,-44],[154,-10],[112,-10],[112,-44]]]}}
  ]
}
